[
  {
    "line": 1,
    "elements": [
      {
        "before": [
          {
            "result": {
              "duration": 2404300,
              "status": "passed"
            },
            "match": {
              "location": "Hooksconcept.SetupApi()"
            }
          },
          {
            "result": {
              "duration": 744000,
              "status": "passed"
            },
            "match": {
              "location": "Taggedhooks.BeforeFirst()"
            }
          }
        ],
        "line": 4,
        "name": "This is First test",
        "description": "",
        "id": "test-tagged-hooks;this-is-first-test",
        "after": [
          {
            "result": {
              "duration": 1826700,
              "status": "passed"
            },
            "match": {
              "location": "Hooksconcept.teardown()"
            }
          },
          {
            "result": {
              "duration": 887600,
              "status": "passed"
            },
            "match": {
              "location": "Taggedhooks.afterfirst()"
            }
          }
        ],
        "type": "scenario",
        "keyword": "Scenario",
        "steps": [
          {
            "result": {
              "duration": 209938200,
              "status": "passed"
            },
            "line": 5,
            "name": "this is the first step",
            "match": {
              "location": "Taggedhooks.this_is_the_first_step()"
            },
            "keyword": "Given "
          },
          {
            "result": {
              "duration": 402600,
              "status": "passed"
            },
            "line": 6,
            "name": "this is the second step",
            "match": {
              "location": "Taggedhooks.this_is_the_second_step()"
            },
            "keyword": "When "
          },
          {
            "result": {
              "duration": 497800,
              "status": "passed"
            },
            "line": 7,
            "name": "this is the third step",
            "match": {
              "location": "Taggedhooks.this_is_the_third_step()"
            },
            "keyword": "Then "
          }
        ],
        "tags": [
          {
            "line": 3,
            "name": "@First"
          }
        ]
      },
      {
        "before": [
          {
            "result": {
              "duration": 503900,
              "status": "passed"
            },
            "match": {
              "location": "Hooksconcept.SetupApi()"
            }
          }
        ],
        "line": 10,
        "name": "This is Second test",
        "description": "",
        "id": "test-tagged-hooks;this-is-second-test",
        "after": [
          {
            "result": {
              "duration": 381100,
              "status": "passed"
            },
            "match": {
              "location": "Hooksconcept.teardown()"
            }
          }
        ],
        "type": "scenario",
        "keyword": "Scenario",
        "steps": [
          {
            "result": {
              "duration": 2463800,
              "status": "passed"
            },
            "line": 11,
            "name": "this is the first step",
            "match": {
              "location": "Taggedhooks.this_is_the_first_step()"
            },
            "keyword": "Given "
          },
          {
            "result": {
              "duration": 3850700,
              "status": "passed"
            },
            "line": 12,
            "name": "this is the second step",
            "match": {
              "location": "Taggedhooks.this_is_the_second_step()"
            },
            "keyword": "When "
          },
          {
            "result": {
              "duration": 2178200,
              "status": "passed"
            },
            "line": 13,
            "name": "this is the third step",
            "match": {
              "location": "Taggedhooks.this_is_the_third_step()"
            },
            "keyword": "Then "
          }
        ],
        "tags": [
          {
            "line": 9,
            "name": "@Second"
          }
        ]
      },
      {
        "before": [
          {
            "result": {
              "duration": 1202200,
              "status": "passed"
            },
            "match": {
              "location": "Hooksconcept.SetupApi()"
            }
          }
        ],
        "line": 16,
        "name": "This is Third test",
        "description": "",
        "id": "test-tagged-hooks;this-is-third-test",
        "after": [
          {
            "result": {
              "duration": 232700,
              "status": "passed"
            },
            "match": {
              "location": "Hooksconcept.teardown()"
            }
          }
        ],
        "type": "scenario",
        "keyword": "Scenario",
        "steps": [
          {
            "result": {
              "duration": 175000,
              "status": "passed"
            },
            "line": 17,
            "name": "this is the first step",
            "match": {
              "location": "Taggedhooks.this_is_the_first_step()"
            },
            "keyword": "Given "
          },
          {
            "result": {
              "duration": 126700,
              "status": "passed"
            },
            "line": 18,
            "name": "this is the second step",
            "match": {
              "location": "Taggedhooks.this_is_the_second_step()"
            },
            "keyword": "When "
          },
          {
            "result": {
              "duration": 85700,
              "status": "passed"
            },
            "line": 19,
            "name": "this is the third step",
            "match": {
              "location": "Taggedhooks.this_is_the_third_step()"
            },
            "keyword": "Then "
          }
        ],
        "tags": [
          {
            "line": 15,
            "name": "@Third"
          }
        ]
      }
    ],
    "name": "Test Tagged Hooks",
    "description": "",
    "id": "test-tagged-hooks",
    "keyword": "Feature",
    "uri": "C:/Users/deepz_patil/git/CucumberTest/MavenCucumberTest/feature/taggedhooks.feature"
  }
]